{
    "2330.TW": {
        "price": 2450.0,
        "rsi": 55.791181144224346,
        "universes": {
            "DYN_1": {
                "shares": 0,
                "value": 0.0,
                "stop_price": 0.0,
                "est_buy_shares": 14,
                "action": "觀望"
            },
            "DYN_2": {
                "shares": 0,
                "value": 0.0,
                "stop_price": 0.0,
                "est_buy_shares": 14,
                "action": "觀望"
            },
            "STA_1": {
                "shares": 0,
                "value": 0.0,
                "stop_price": 0.0,
                "est_buy_shares": 14,
                "action": "觀望"
            },
            "STA_2": {
                "shares": 0,
                "value": 0.0,
                "stop_price": 0.0,
                "est_buy_shares": 14,
                "action": "觀望"
            }
        }
    },
    "2317.TW": {
        "price": 240.0,
        "rsi": 46.46285450098073,
        "universes": {
            "DYN_1": {
                "shares": 0,
                "value": 0.0,
                "stop_price": 0.0,
                "est_buy_shares": 115,
                "action": "觀望"
            },
            "DYN_2": {
                "shares": 0,
                "value": 0.0,
                "stop_price": 0.0,
                "est_buy_shares": 110,
                "action": "觀望"
            },
            "STA_1": {
                "shares": 0,
                "value": 0.0,
                "stop_price": 0.0,
                "est_buy_shares": 115,
                "action": "觀望"
            },
            "STA_2": {
                "shares": 0,
                "value": 0.0,
                "stop_price": 0.0,
                "est_buy_shares": 110,
                "action": "觀望"
            }
        }
    },
    "2454.TW": {
        "price": 3745.0,
        "rsi": 42.53828855775483,
        "universes": {
            "DYN_1": {
                "shares": 0,
                "value": 0.0,
                "stop_price": 0.0,
                "est_buy_shares": 3,
                "action": "觀望"
            },
            "DYN_2": {
                "shares": 0,
                "value": 0.0,
                "stop_price": 0.0,
                "est_buy_shares": 3,
                "action": "觀望"
            },
            "STA_1": {
                "shares": 0,
                "value": 0.0,
                "stop_price": 0.0,
                "est_buy_shares": 3,
                "action": "觀望"
            },
            "STA_2": {
                "shares": 0,
                "value": 0.0,
                "stop_price": 0.0,
                "est_buy_shares": 3,
                "action": "觀望"
            }
        }
    },
    "2308.TW": {
        "price": 1910.0,
        "rsi": 42.76141688404785,
        "universes": {
            "DYN_1": {
                "shares": 0,
                "value": 0.0,
                "stop_price": 0.0,
                "est_buy_shares": 7,
                "action": "觀望"
            },
            "DYN_2": {
                "shares": 0,
                "value": 0.0,
                "stop_price": 0.0,
                "est_buy_shares": 7,
                "action": "觀望"
            },
            "STA_1": {
                "shares": 0,
                "value": 0.0,
                "stop_price": 0.0,
                "est_buy_shares": 7,
                "action": "觀望"
            },
            "STA_2": {
                "shares": 0,
                "value": 0.0,
                "stop_price": 0.0,
                "est_buy_shares": 7,
                "action": "觀望"
            }
        }
    },
    "2382.TW": {
        "price": 381.0,
        "rsi": 57.99130459244875,
        "universes": {
            "DYN_1": {
                "shares": 0,
                "value": 0.0,
                "stop_price": 0.0,
                "est_buy_shares": 72,
                "action": "觀望"
            },
            "DYN_2": {
                "shares": 0,
                "value": 0.0,
                "stop_price": 0.0,
                "est_buy_shares": 69,
                "action": "觀望"
            },
            "STA_1": {
                "shares": 0,
                "value": 0.0,
                "stop_price": 0.0,
                "est_buy_shares": 72,
                "action": "觀望"
            },
            "STA_2": {
                "shares": 0,
                "value": 0.0,
                "stop_price": 0.0,
                "est_buy_shares": 69,
                "action": "觀望"
            }
        }
    },
    "2881.TW": {
        "price": 129.5,
        "rsi": 63.09241883813981,
        "universes": {
            "DYN_1": {
                "shares": 0,
                "value": 0.0,
                "stop_price": 0.0,
                "est_buy_shares": 190,
                "action": "觀望"
            },
            "DYN_2": {
                "shares": 0,
                "value": 0.0,
                "stop_price": 0.0,
                "est_buy_shares": 182,
                "action": "觀望"
            },
            "STA_1": {
                "shares": 0,
                "value": 0.0,
                "stop_price": 0.0,
                "est_buy_shares": 190,
                "action": "觀望"
            },
            "STA_2": {
                "shares": 0,
                "value": 0.0,
                "stop_price": 0.0,
                "est_buy_shares": 182,
                "action": "觀望"
            }
        }
    },
    "2886.TW": {
        "price": 46.25,
        "rsi": 60.249243605696826,
        "universes": {
            "DYN_1": {
                "shares": 0,
                "value": 0.0,
                "stop_price": 0.0,
                "est_buy_shares": 760,
                "action": "觀望"
            },
            "DYN_2": {
                "shares": 0,
                "value": 0.0,
                "stop_price": 0.0,
                "est_buy_shares": 726,
                "action": "觀望"
            },
            "STA_1": {
                "shares": 0,
                "value": 0.0,
                "stop_price": 0.0,
                "est_buy_shares": 760,
                "action": "觀望"
            },
            "STA_2": {
                "shares": 0,
                "value": 0.0,
                "stop_price": 0.0,
                "est_buy_shares": 726,
                "action": "觀望"
            }
        }
    },
    "2891.TW": {
        "price": 63.900001525878906,
        "rsi": 42.89139423119155,
        "universes": {
            "DYN_1": {
                "shares": 0,
                "value": 0.0,
                "stop_price": 0.0,
                "est_buy_shares": 385,
                "action": "觀望"
            },
            "DYN_2": {
                "shares": 0,
                "value": 0.0,
                "stop_price": 0.0,
                "est_buy_shares": 368,
                "action": "觀望"
            },
            "STA_1": {
                "shares": 0,
                "value": 0.0,
                "stop_price": 0.0,
                "est_buy_shares": 385,
                "action": "觀望"
            },
            "STA_2": {
                "shares": 0,
                "value": 0.0,
                "stop_price": 0.0,
                "est_buy_shares": 368,
                "action": "觀望"
            }
        }
    },
    "2603.TW": {
        "price": 199.0,
        "rsi": 56.03632952418801,
        "universes": {
            "DYN_1": {
                "shares": 82,
                "value": 16318.0,
                "stop_price": 182.98349495310458,
                "est_buy_shares": 155,
                "action": "🤝 抱牢波段"
            },
            "DYN_2": {
                "shares": 102,
                "value": 20298.0,
                "stop_price": 188.32232996873637,
                "est_buy_shares": 149,
                "action": "🤝 抱牢波段"
            },
            "STA_1": {
                "shares": 82,
                "value": 16318.0,
                "stop_price": 182.98349495310458,
                "est_buy_shares": 155,
                "action": "🤝 抱牢波段"
            },
            "STA_2": {
                "shares": 102,
                "value": 20298.0,
                "stop_price": 188.32232996873637,
                "est_buy_shares": 149,
                "action": "🤝 抱牢波段"
            }
        }
    },
    "2002.TW": {
        "price": 18.75,
        "rsi": 48.45574111307809,
        "universes": {
            "DYN_1": {
                "shares": 0,
                "value": 0.0,
                "stop_price": 0.0,
                "est_buy_shares": 2433,
                "action": "觀望"
            },
            "DYN_2": {
                "shares": 0,
                "value": 0.0,
                "stop_price": 0.0,
                "est_buy_shares": 2326,
                "action": "觀望"
            },
            "STA_1": {
                "shares": 0,
                "value": 0.0,
                "stop_price": 0.0,
                "est_buy_shares": 2433,
                "action": "觀望"
            },
            "STA_2": {
                "shares": 0,
                "value": 0.0,
                "stop_price": 0.0,
                "est_buy_shares": 2326,
                "action": "觀望"
            }
        }
    }
}