{
    "2330.TW": {
        "price": 2385.0,
        "rsi": 48.56089759335822,
        "universes": {
            "DYN_1": {
                "shares": 0,
                "value": 0.0,
                "stop_price": 0.0,
                "est_buy_shares": 8,
                "action": "觀望"
            },
            "DYN_2": {
                "shares": 0,
                "value": 0.0,
                "stop_price": 0.0,
                "est_buy_shares": 7,
                "action": "觀望"
            },
            "STA_1": {
                "shares": 0,
                "value": 0.0,
                "stop_price": 0.0,
                "est_buy_shares": 8,
                "action": "觀望"
            },
            "STA_2": {
                "shares": 0,
                "value": 0.0,
                "stop_price": 0.0,
                "est_buy_shares": 7,
                "action": "觀望"
            }
        }
    },
    "2317.TW": {
        "price": 245.5,
        "rsi": 51.59272468165648,
        "universes": {
            "DYN_1": {
                "shares": 68,
                "value": 16694.0,
                "stop_price": 222.33371145326865,
                "est_buy_shares": 69,
                "action": "🤝 抱牢波段"
            },
            "DYN_2": {
                "shares": 65,
                "value": 15957.5,
                "stop_price": 230.05580763551242,
                "est_buy_shares": 66,
                "action": "🤝 抱牢波段"
            },
            "STA_1": {
                "shares": 68,
                "value": 16694.0,
                "stop_price": 222.33371145326865,
                "est_buy_shares": 69,
                "action": "🤝 抱牢波段"
            },
            "STA_2": {
                "shares": 65,
                "value": 15957.5,
                "stop_price": 230.05580763551242,
                "est_buy_shares": 66,
                "action": "🤝 抱牢波段"
            }
        }
    },
    "2454.TW": {
        "price": 3585.0,
        "rsi": 42.139184356152974,
        "universes": {
            "DYN_1": {
                "shares": 0,
                "value": 0.0,
                "stop_price": 0.0,
                "est_buy_shares": 2,
                "action": "觀望"
            },
            "DYN_2": {
                "shares": 0,
                "value": 0.0,
                "stop_price": 0.0,
                "est_buy_shares": 2,
                "action": "觀望"
            },
            "STA_1": {
                "shares": 0,
                "value": 0.0,
                "stop_price": 0.0,
                "est_buy_shares": 2,
                "action": "觀望"
            },
            "STA_2": {
                "shares": 0,
                "value": 0.0,
                "stop_price": 0.0,
                "est_buy_shares": 2,
                "action": "觀望"
            }
        }
    },
    "2308.TW": {
        "price": 1820.0,
        "rsi": 42.74249381537914,
        "universes": {
            "DYN_1": {
                "shares": 0,
                "value": 0.0,
                "stop_price": 0.0,
                "est_buy_shares": 4,
                "action": "觀望"
            },
            "DYN_2": {
                "shares": 0,
                "value": 0.0,
                "stop_price": 0.0,
                "est_buy_shares": 4,
                "action": "觀望"
            },
            "STA_1": {
                "shares": 0,
                "value": 0.0,
                "stop_price": 0.0,
                "est_buy_shares": 4,
                "action": "觀望"
            },
            "STA_2": {
                "shares": 0,
                "value": 0.0,
                "stop_price": 0.0,
                "est_buy_shares": 4,
                "action": "觀望"
            }
        }
    },
    "2382.TW": {
        "price": 321.0,
        "rsi": 34.26957892726729,
        "universes": {
            "DYN_1": {
                "shares": 0,
                "value": 0.0,
                "stop_price": 0.0,
                "est_buy_shares": 41,
                "action": "觀望"
            },
            "DYN_2": {
                "shares": 0,
                "value": 0.0,
                "stop_price": 0.0,
                "est_buy_shares": 39,
                "action": "觀望"
            },
            "STA_1": {
                "shares": 0,
                "value": 0.0,
                "stop_price": 0.0,
                "est_buy_shares": 41,
                "action": "觀望"
            },
            "STA_2": {
                "shares": 0,
                "value": 0.0,
                "stop_price": 0.0,
                "est_buy_shares": 39,
                "action": "觀望"
            }
        }
    },
    "2881.TW": {
        "price": 123.5,
        "rsi": 52.43984208120946,
        "universes": {
            "DYN_1": {
                "shares": 0,
                "value": 0.0,
                "stop_price": 0.0,
                "est_buy_shares": 129,
                "action": "觀望"
            },
            "DYN_2": {
                "shares": 0,
                "value": 0.0,
                "stop_price": 0.0,
                "est_buy_shares": 123,
                "action": "觀望"
            },
            "STA_1": {
                "shares": 0,
                "value": 0.0,
                "stop_price": 0.0,
                "est_buy_shares": 129,
                "action": "觀望"
            },
            "STA_2": {
                "shares": 0,
                "value": 0.0,
                "stop_price": 0.0,
                "est_buy_shares": 123,
                "action": "觀望"
            }
        }
    },
    "2886.TW": {
        "price": 48.45000076293945,
        "rsi": 72.16115392819427,
        "universes": {
            "DYN_1": {
                "shares": 0,
                "value": 0.0,
                "stop_price": 0.0,
                "est_buy_shares": 476,
                "action": "觀望"
            },
            "DYN_2": {
                "shares": 0,
                "value": 0.0,
                "stop_price": 0.0,
                "est_buy_shares": 455,
                "action": "觀望"
            },
            "STA_1": {
                "shares": 0,
                "value": 0.0,
                "stop_price": 0.0,
                "est_buy_shares": 476,
                "action": "觀望"
            },
            "STA_2": {
                "shares": 0,
                "value": 0.0,
                "stop_price": 0.0,
                "est_buy_shares": 455,
                "action": "觀望"
            }
        }
    },
    "2891.TW": {
        "price": 63.099998474121094,
        "rsi": 43.359121541951446,
        "universes": {
            "DYN_1": {
                "shares": 0,
                "value": 0.0,
                "stop_price": 0.0,
                "est_buy_shares": 258,
                "action": "觀望"
            },
            "DYN_2": {
                "shares": 0,
                "value": 0.0,
                "stop_price": 0.0,
                "est_buy_shares": 247,
                "action": "觀望"
            },
            "STA_1": {
                "shares": 0,
                "value": 0.0,
                "stop_price": 0.0,
                "est_buy_shares": 258,
                "action": "觀望"
            },
            "STA_2": {
                "shares": 0,
                "value": 0.0,
                "stop_price": 0.0,
                "est_buy_shares": 247,
                "action": "觀望"
            }
        }
    },
    "2603.TW": {
        "price": 204.0,
        "rsi": 60.37162058813325,
        "universes": {
            "DYN_1": {
                "shares": 82,
                "value": 16728.0,
                "stop_price": 187.24560057128062,
                "est_buy_shares": 95,
                "action": "🤝 抱牢波段"
            },
            "DYN_2": {
                "shares": 102,
                "value": 20808.0,
                "stop_price": 192.83040038085375,
                "est_buy_shares": 91,
                "action": "🤝 抱牢波段"
            },
            "STA_1": {
                "shares": 82,
                "value": 16728.0,
                "stop_price": 187.24560057128062,
                "est_buy_shares": 95,
                "action": "🤝 抱牢波段"
            },
            "STA_2": {
                "shares": 102,
                "value": 20808.0,
                "stop_price": 192.83040038085375,
                "est_buy_shares": 91,
                "action": "🤝 抱牢波段"
            }
        }
    },
    "2002.TW": {
        "price": 18.799999237060547,
        "rsi": 51.05181379264799,
        "universes": {
            "DYN_1": {
                "shares": 707,
                "value": 13291.599460601807,
                "stop_price": 17.766210216530194,
                "est_buy_shares": 1549,
                "action": "🤝 抱牢波段"
            },
            "DYN_2": {
                "shares": 677,
                "value": 12727.59948348999,
                "stop_price": 18.110806556706976,
                "est_buy_shares": 1481,
                "action": "🤝 抱牢波段"
            },
            "STA_1": {
                "shares": 707,
                "value": 13291.599460601807,
                "stop_price": 17.766210216530194,
                "est_buy_shares": 1549,
                "action": "🤝 抱牢波段"
            },
            "STA_2": {
                "shares": 677,
                "value": 12727.59948348999,
                "stop_price": 18.110806556706976,
                "est_buy_shares": 1481,
                "action": "🤝 抱牢波段"
            }
        }
    }
}