{
    "2330.TW": {
        "price": 2350.0,
        "rsi": 48.33262564065004,
        "universes": {
            "DYN_1": {
                "shares": 0,
                "value": 0.0,
                "stop_price": 0.0,
                "est_buy_shares": 6,
                "action": "觀望"
            },
            "DYN_2": {
                "shares": 0,
                "value": 0.0,
                "stop_price": 0.0,
                "est_buy_shares": 6,
                "action": "觀望"
            },
            "STA_1": {
                "shares": 0,
                "value": 0.0,
                "stop_price": 0.0,
                "est_buy_shares": 6,
                "action": "觀望"
            },
            "STA_2": {
                "shares": 0,
                "value": 0.0,
                "stop_price": 0.0,
                "est_buy_shares": 6,
                "action": "觀望"
            }
        }
    },
    "2317.TW": {
        "price": 252.0,
        "rsi": 56.849258471264115,
        "universes": {
            "DYN_1": {
                "shares": 68,
                "value": 17136.0,
                "stop_price": 233.46671618222203,
                "est_buy_shares": 52,
                "action": "🤝 抱牢波段"
            },
            "DYN_2": {
                "shares": 65,
                "value": 16380.0,
                "stop_price": 241.47781078814802,
                "est_buy_shares": 49,
                "action": "🤝 抱牢波段"
            },
            "STA_1": {
                "shares": 68,
                "value": 17136.0,
                "stop_price": 233.46671618222203,
                "est_buy_shares": 52,
                "action": "🤝 抱牢波段"
            },
            "STA_2": {
                "shares": 65,
                "value": 16380.0,
                "stop_price": 241.47781078814802,
                "est_buy_shares": 49,
                "action": "🤝 抱牢波段"
            }
        }
    },
    "2454.TW": {
        "price": 3785.0,
        "rsi": 48.42981669623548,
        "universes": {
            "DYN_1": {
                "shares": 1,
                "value": 3785.0,
                "stop_price": 3060.6162649126763,
                "est_buy_shares": 1,
                "action": "🤝 抱牢波段"
            },
            "DYN_2": {
                "shares": 1,
                "value": 3785.0,
                "stop_price": 3302.0775099417842,
                "est_buy_shares": 1,
                "action": "🤝 抱牢波段"
            },
            "STA_1": {
                "shares": 1,
                "value": 3785.0,
                "stop_price": 3060.6162649126763,
                "est_buy_shares": 1,
                "action": "🤝 抱牢波段"
            },
            "STA_2": {
                "shares": 1,
                "value": 3785.0,
                "stop_price": 3302.0775099417842,
                "est_buy_shares": 1,
                "action": "🤝 抱牢波段"
            }
        }
    },
    "2308.TW": {
        "price": 1795.0,
        "rsi": 41.35984361609204,
        "universes": {
            "DYN_1": {
                "shares": 0,
                "value": 0.0,
                "stop_price": 1537.2550074390506,
                "est_buy_shares": 4,
                "action": "⚠️ 破底逃命"
            },
            "DYN_2": {
                "shares": 0,
                "value": 0.0,
                "stop_price": 1651.5033382927004,
                "est_buy_shares": 4,
                "action": "⚠️ 破底逃命"
            },
            "STA_1": {
                "shares": 0,
                "value": 0.0,
                "stop_price": 1537.2550074390506,
                "est_buy_shares": 4,
                "action": "⚠️ 破底逃命"
            },
            "STA_2": {
                "shares": 0,
                "value": 0.0,
                "stop_price": 1651.5033382927004,
                "est_buy_shares": 4,
                "action": "⚠️ 破底逃命"
            }
        }
    },
    "2382.TW": {
        "price": 328.5,
        "rsi": 41.49131117635184,
        "universes": {
            "DYN_1": {
                "shares": 0,
                "value": 0.0,
                "stop_price": 0.0,
                "est_buy_shares": 39,
                "action": "觀望"
            },
            "DYN_2": {
                "shares": 0,
                "value": 0.0,
                "stop_price": 0.0,
                "est_buy_shares": 37,
                "action": "觀望"
            },
            "STA_1": {
                "shares": 0,
                "value": 0.0,
                "stop_price": 0.0,
                "est_buy_shares": 39,
                "action": "觀望"
            },
            "STA_2": {
                "shares": 0,
                "value": 0.0,
                "stop_price": 0.0,
                "est_buy_shares": 37,
                "action": "觀望"
            }
        }
    },
    "2881.TW": {
        "price": 127.5,
        "rsi": 58.34073013060207,
        "universes": {
            "DYN_1": {
                "shares": 0,
                "value": 0.0,
                "stop_price": 0.0,
                "est_buy_shares": 119,
                "action": "觀望"
            },
            "DYN_2": {
                "shares": 0,
                "value": 0.0,
                "stop_price": 0.0,
                "est_buy_shares": 113,
                "action": "觀望"
            },
            "STA_1": {
                "shares": 0,
                "value": 0.0,
                "stop_price": 0.0,
                "est_buy_shares": 119,
                "action": "觀望"
            },
            "STA_2": {
                "shares": 0,
                "value": 0.0,
                "stop_price": 0.0,
                "est_buy_shares": 113,
                "action": "觀望"
            }
        }
    },
    "2886.TW": {
        "price": 48.400001525878906,
        "rsi": 68.78346986218556,
        "universes": {
            "DYN_1": {
                "shares": 0,
                "value": 0.0,
                "stop_price": 0.0,
                "est_buy_shares": 429,
                "action": "觀望"
            },
            "DYN_2": {
                "shares": 0,
                "value": 0.0,
                "stop_price": 0.0,
                "est_buy_shares": 409,
                "action": "觀望"
            },
            "STA_1": {
                "shares": 0,
                "value": 0.0,
                "stop_price": 0.0,
                "est_buy_shares": 429,
                "action": "觀望"
            },
            "STA_2": {
                "shares": 0,
                "value": 0.0,
                "stop_price": 0.0,
                "est_buy_shares": 409,
                "action": "觀望"
            }
        }
    },
    "2891.TW": {
        "price": 63.5,
        "rsi": 45.487141563231326,
        "universes": {
            "DYN_1": {
                "shares": 0,
                "value": 0.0,
                "stop_price": 0.0,
                "est_buy_shares": 245,
                "action": "觀望"
            },
            "DYN_2": {
                "shares": 0,
                "value": 0.0,
                "stop_price": 0.0,
                "est_buy_shares": 233,
                "action": "觀望"
            },
            "STA_1": {
                "shares": 0,
                "value": 0.0,
                "stop_price": 0.0,
                "est_buy_shares": 245,
                "action": "觀望"
            },
            "STA_2": {
                "shares": 0,
                "value": 0.0,
                "stop_price": 0.0,
                "est_buy_shares": 233,
                "action": "觀望"
            }
        }
    },
    "2603.TW": {
        "price": 205.0,
        "rsi": 60.675142855766694,
        "universes": {
            "DYN_1": {
                "shares": 82,
                "value": 16810.0,
                "stop_price": 190.23655872701917,
                "est_buy_shares": 93,
                "action": "🤝 抱牢波段"
            },
            "DYN_2": {
                "shares": 102,
                "value": 20910.0,
                "stop_price": 195.49103915134611,
                "est_buy_shares": 88,
                "action": "🤝 抱牢波段"
            },
            "STA_1": {
                "shares": 82,
                "value": 16810.0,
                "stop_price": 190.23655872701917,
                "est_buy_shares": 93,
                "action": "🤝 抱牢波段"
            },
            "STA_2": {
                "shares": 102,
                "value": 20910.0,
                "stop_price": 195.49103915134611,
                "est_buy_shares": 88,
                "action": "🤝 抱牢波段"
            }
        }
    },
    "2002.TW": {
        "price": 19.149999618530273,
        "rsi": 60.07187795236517,
        "universes": {
            "DYN_1": {
                "shares": 707,
                "value": 13539.049730300903,
                "stop_price": 18.066846527059738,
                "est_buy_shares": 1356,
                "action": "🤝 抱牢波段"
            },
            "DYN_2": {
                "shares": 677,
                "value": 12964.549741744995,
                "stop_price": 18.427897557549915,
                "est_buy_shares": 1291,
                "action": "🤝 抱牢波段"
            },
            "STA_1": {
                "shares": 707,
                "value": 13539.049730300903,
                "stop_price": 18.066846527059738,
                "est_buy_shares": 1356,
                "action": "🤝 抱牢波段"
            },
            "STA_2": {
                "shares": 677,
                "value": 12964.549741744995,
                "stop_price": 18.427897557549915,
                "est_buy_shares": 1291,
                "action": "🤝 抱牢波段"
            }
        }
    }
}